ensuro/__init__.py
ensuro/prototype.py
ensuro/utils.py
ensuro/wrappers.py
ensuro/contracts/AccessManager.json
ensuro/contracts/ERC1967Proxy.json
ensuro/contracts/ERC4626AssetManager.json
ensuro/contracts/ERC4626PlusVaultAssetManager.json
ensuro/contracts/EToken.json
ensuro/contracts/IAccessManager.json
ensuro/contracts/IAssetManager.json
ensuro/contracts/IERC20.json
ensuro/contracts/IERC20Metadata.json
ensuro/contracts/IERC721.json
ensuro/contracts/IEToken.json
ensuro/contracts/ILPWhitelist.json
ensuro/contracts/IPolicyHolder.json
ensuro/contracts/IPolicyHolderV2.json
ensuro/contracts/IPolicyPool.json
ensuro/contracts/IPolicyPoolComponent.json
ensuro/contracts/IPremiumsAccount.json
ensuro/contracts/IRiskModule.json
ensuro/contracts/LPManualWhitelist.json
ensuro/contracts/LiquidityThresholdAssetManager.json
ensuro/contracts/Policy.json
ensuro/contracts/PolicyPool.json
ensuro/contracts/PolicyPoolComponent.json
ensuro/contracts/PremiumsAccount.json
ensuro/contracts/Reserve.json
ensuro/contracts/RiskModule.json
ensuro/contracts/SignedBucketRiskModule.json
ensuro/contracts/SignedQuoteRiskModule.json
ensuro/contracts/TestCurrency.json
ensuro/contracts/TimeScaled.json
ensuro/contracts/TrustfulRiskModule.json
ensuro/contracts/__init__.py
ensuro-2.8.3.dist-info/LICENSE.txt
ensuro-2.8.3.dist-info/METADATA
ensuro-2.8.3.dist-info/WHEEL
ensuro-2.8.3.dist-info/top_level.txt
ensuro-2.8.3.dist-info/RECORD
