Metadata-Version: 2.1
Name: ensuro
Version: 2.8.3
Summary: Prototype and wrappers to work with Ensuro Smart Contracts
Home-page: https://github.com/ensuro/ensuro/
Author: Guillermo M. Narvaja
Author-email: guillermo@ensuro.co
License: Apache-2.0
Project-URL: Documentation, https://docs.ensuro.co/
Project-URL: Source, https://github.com/ensuro/ensuro/
Platform: any
Classifier: Development Status :: 5 - Production/Stable
Classifier: Programming Language :: Python
Requires-Python: >=3.9
License-File: LICENSE.txt
Requires-Dist: pyyaml>=5.1
Requires-Dist: eth-prototype>=1.0.1
Requires-Dist: importlib-metadata; python_version < "3.8"
Provides-Extra: testing
Requires-Dist: setuptools; extra == "testing"
Requires-Dist: pytest; extra == "testing"
Requires-Dist: pytest-cov; extra == "testing"
Requires-Dist: ipdb; extra == "testing"
Requires-Dist: web3[tester]; extra == "testing"
Requires-Dist: eth-prototype[web3]>=1.0.1; extra == "testing"
Provides-Extra: web3
Requires-Dist: eth-prototype[web3]>=1.0.1; extra == "web3"
